<?xml version="1.0" encoding="utf-8"?>
<ZWaveDevice xmlns="http://www.pepper1.net/zwavedb/xml-schemata/z-wave" schemaVersion="2"><descriptorVersion>1</descriptorVersion><deviceData><manufacturerId value="0117"/><productType value="0001"/><productId value="0080"/><protoVersion value="06"/><protoSubVersion value="51"/><appVersion value="00"/><appSubVersion value="00"/><basicClass value="04"/><genericClass value="00"/><specificClass value="00"/><beamSensor>0</beamSensor><certNumber>ZC10-15100023</certNumber><rfFrequency>EU</rfFrequency></deviceData><deviceDescription><description><lang xml:lang="en">IndependenceGewa Andromeda socket is specially adapted for disabled people who want to live a more independent life, such as wireless, can turn on/off lights, turn on/off various devices and can easily be moved between different outlets.Flexible control modesIt can be controlled in three different ways, with an IR transmitter (GewaLink system), a radio transmitter (Z-Wave) or a connected control switch.Built-in on/off buttonAndromeda Socket also has a built-in on/off switch that makes you always can operate the device even if one has no IR/radio transmitter. It also has a blue indicator light that shows if the switch is on.Easy to programIt is easy to program, as is done with the built-in on/off button.Andromeda socket available in different versions for different countries.Technical dataOperating voltage: 230V AC, 50 HzMaximum load: 3600VA 16A resistive loadProgramming Channels IR: GewaLink channelsRadio: Z-waveRadio frequency: 868.42 MHzSocket for control switch: 3.5 mm (2-pole mono female)Operating environment: indoors (IP 21)Dimensions: 53 x 122 x 43mm (excluding connector plug)</lang></description><productName>Gewa Andromeda Socket FR</productName><brandName>Abilia AB</brandName><productCode>419882</productCode></deviceDescription><commandClasses><commandClass id="005e" supported="true" controlled="false"/></commandClasses><assocGroups><assocGroup number="1" maxNodes="5"><description><lang xml:lang="en">Z-Wave Plus Lifeline, DEVICE_RESET_LOCALLY_NOTIFICATION, SWITCH_BINARY_REPORT</lang></description></assocGroup></assocGroups><resourceLinks><deviceImage url="https://products.z-wavealliance.org/ProductImages/Index?productName=ZC10-15100023"/></resourceLinks></ZWaveDevice>
