<?xml version="1.0" encoding="utf-8"?>
<ZWaveDevice xmlns="http://www.pepper1.net/zwavedb/xml-schemata/z-wave" schemaVersion="2"><descriptorVersion>1</descriptorVersion><deviceData><manufacturerId value="016A"/><productType value="0103"/><productId value="0060"/><protoVersion value="06"/><protoSubVersion value="51"/><appVersion value="00"/><appSubVersion value="00"/><basicClass value="03"/><genericClass value="00"/><specificClass value="00"/><beamSensor>0</beamSensor><certNumber>ZC10-15110005</certNumber><rfFrequency>US</rfFrequency></deviceData><deviceDescription><description><lang xml:lang="en">Oomi Plug is a low-cost Z-Wave Switch plug-in module specifically used to enable Z-Wave command and control (on/off) of any plug-in tool. It can report immediate wattage consumption or kWh energy usage over a period of time. In the event of power failure, non-volatile memory retains all programmed information relating to the units operating status.Its surface has a Smart RGB LED, which can be used for indicating the output load status or strength of the wireless signal. You can configure its indication colour according to your favour.The Plug is also a security Z-wave device and supports Over The Air (OTA) feature for the products firmware upgrade.</lang></description><productName>Plug</productName><brandName>Oomi</brandName><productCode>FT096-A02</productCode></deviceDescription><commandClasses><commandClass id="005e" supported="true" controlled="false"/></commandClasses><assocGroups><assocGroup number="1" maxNodes="5"><description><lang xml:lang="en">Group 1 is assigned to the Lifeline association group and every device has 5 nodes to associate.When the switch is turned on or off using the action button, the switch will send a basic report of its status to the nodes in association group 1. To change what kind of signal is sent to the nodes in group 1, please see the detailed description of configuration parameter 80.</lang></description></assocGroup><assocGroup number="2" maxNodes="5"><description><lang xml:lang="en">When the product receives a controlling Basic Set CC/Switch Binary Set CC, which if cause the products load state to be changed, which will lead to send the Basic Set CC/Switch Binary Set CC to nodes in group 2.</lang></description></assocGroup></assocGroups><configParams><configParam number="101" size="4" default="4" type="rangemapped"><name><lang xml:lang="en">To set which report need to be sent.</lang></name><description><lang xml:lang="en">This parameter is used to configure which reports need to be sent in Report Group 1.The values corresponding to the first four bits of the parameter value may be combined to create different combinations of reports that you wish to have sent.For example, instantaneous Current is the value 2 and instantaneous Watts is the value 4, so setting parameter 101 to a value of 6 will result in both instantaneous Current and instantaneous Watts to be reported.See the full description of the parameter values for other possible settings.</lang></description><value from="8" to="8"><description><lang xml:lang="en">Report Accumulated kWh</lang></description></value><value from="2" to="2"><description><lang xml:lang="en">Report Instantaneous Current (Amperes)</lang></description></value><value from="4" to="4"><description><lang xml:lang="en">Report Instantaneous Watts</lang></description></value><value from="1" to="1"><description><lang xml:lang="en">Report Instantaneous Voltage</lang></description></value></configParam><configParam number="102" size="4" default="8" type="rangemapped"><name><lang xml:lang="en">To set which report need to be sent.</lang></name><description><lang xml:lang="en">This parameter is used to configure which reports need to be sent in Report Group 2.The values corresponding to the first four bits of the parameter value may be combined to create different combinations of reports that you wish to have sent.For example, instantaneous Current is the value 2 and instantaneous Watts is the value 4, so setting parameter 102 to a value of 6 will result in both instantaneous Current and instantaneous Watts to be reported.See the full description of the parameter values for other possible settings.</lang></description><value from="1" to="1"><description><lang xml:lang="en">Report Instantaneous Voltage</lang></description></value><value from="4" to="4"><description><lang xml:lang="en">Report Instantaneous Watts</lang></description></value><value from="8" to="8"><description><lang xml:lang="en">Report Accumulated kWh</lang></description></value><value from="2" to="2"><description><lang xml:lang="en">Report Instantaneous Current (Amperes)</lang></description></value></configParam><configParam number="103" size="4" default="0" type="rangemapped"><name><lang xml:lang="en">To set which report need to be sent.</lang></name><description><lang xml:lang="en">This parameter is used to configure which reports need to be sent in Report Group 3.The values corresponding to the first four bits of the parameter value may be combined to create different combinations of reports that you wish to have sent.For example, instantaneous Current is the value 2 and instantaneous Watts is the value 4, so setting parameter 103 to a value of 6 will result in both instantaneous Current and instantaneous Watts to be reported.See the full description of the parameter values for other possible settings.</lang></description><value from="4" to="4"><description><lang xml:lang="en">Report Instantaneous Watts</lang></description></value><value from="8" to="8"><description><lang xml:lang="en">Report Accumulated kWh</lang></description></value><value from="1" to="1"><description><lang xml:lang="en">Report Instantaneous Voltage</lang></description></value><value from="2" to="2"><description><lang xml:lang="en">Report Instantaneous Current (Amperes)</lang></description></value></configParam><configParam number="111" size="4" default="600" type="range"><name><lang xml:lang="en">Set the interval time of sending report.</lang></name><description><lang xml:lang="en">This parameter is used to set the interval time of sending report in Report Group 1. (The unit of time is second).</lang></description><value from="0" to="268435456"><description><lang xml:lang="en">Interval Seconds</lang></description></value></configParam><configParam number="112" size="4" default="600" type="range"><name><lang xml:lang="en">Set the interval time of sending report.</lang></name><description><lang xml:lang="en">This parameter is used to set the interval time of sending report in Report Group 2. (The unit of time is second).</lang></description><value from="0" to="268435456"><description><lang xml:lang="en">Interval Seconds</lang></description></value></configParam><configParam number="113" size="4" default="600" type="range"><name><lang xml:lang="en">Set the interval time of sending report.</lang></name><description><lang xml:lang="en">This parameter is used to set the interval time of sending report in Report Group 3. (The unit of time is second).</lang></description><value from="0" to="268435456"><description><lang xml:lang="en">Interval Seconds</lang></description></value></configParam><configParam number="20" size="1" default="0" type="rangemapped"><name><lang xml:lang="en">Configure the output load status after re-power on</lang></name><description><lang xml:lang="en">Configure the output load status after re-power on the Smart Switch.</lang></description><value from="0" to="0"><description><lang xml:lang="en">The output load status will be the same as the previous state before a power outage.</lang></description></value><value from="1" to="1"><description><lang xml:lang="en">The output load status will be ON state after re-power on.</lang></description></value><value from="2" to="2"><description><lang xml:lang="en">The output load status will be OFF state after re-power on.</lang></description></value></configParam><configParam number="200" size="1" default="0" type="rangemapped"><name><lang xml:lang="en">Partner ID</lang></name><description><lang xml:lang="en">This parameter is used to configure the partner ID. (0== Aeon Labs Standard Product, 1~255== others).</lang></description><value from="0" to="0"><description><lang xml:lang="en">Aeon Labs Standard Product</lang></description></value><value from="1" to="255"><description><lang xml:lang="en">Partner ID of Partner Product</lang></description></value></configParam><configParam number="252" size="1" default="0" type="rangemapped"><name><lang xml:lang="en">Enable/Disable Lock Configuration</lang></name><description><lang xml:lang="en">This parameter is used to enable/disable Lock all configuration parameters.(0 =disable, 1 = enable)</lang></description><value from="0" to="0"><description><lang xml:lang="en">All configuration parameters are configurable.</lang></description></value><value from="1" to="1"><description><lang xml:lang="en">All configuration parameters are not configurable (Locked).</lang></description></value></configParam><configParam number="254" size="2" default="0" type="range"><name><lang xml:lang="en">Device Tag</lang></name><description><lang xml:lang="en">This parameter is used to save the device tag, which will be written/ assigned in factory/ manufacturer.</lang></description><value from="0" to="32767"><description><lang xml:lang="en">Device Tag</lang></description></value></configParam><configParam number="255" size="4" default="0" type="rangemapped"><name><lang xml:lang="en">Reset to default factory setting</lang></name><description><lang xml:lang="en">This parameter is used to reset product to default factory setting. (There are just 2 values can be used).</lang></description><value from="1431655765" to="1431655765"><description><lang xml:lang="en">Reset the product to default factory setting and be excluded from the Z-wave network.</lang></description></value><value from="1" to="1"><description><lang xml:lang="en">Resets all configuration parameters to default setting.</lang></description></value></configParam><configParam number="3" size="1" default="0" type="rangemapped"><name><lang xml:lang="en">Current Overload Protection</lang></name><description><lang xml:lang="en">This parameter is used for the overload protection, which means the load will be disconnected after 2 minutes when the current more than 15.5A.</lang></description><value from="0" to="0"><description><lang xml:lang="en">Overload Protection Disabled</lang></description></value><value from="1" to="1"><description><lang xml:lang="en">Overload Protection is Enabled</lang></description></value></configParam><configParam number="33" size="4" default="0" type="rangemapped"><name><lang xml:lang="en">Change the color value of RGB LED for testing</lang></name><description><lang xml:lang="en">This parameter is only used for customer checking/testing the product's RGB color via changing the RGB values. </lang></description><value from="0" to="255"><description><lang xml:lang="en">Reserved</lang></description></value><value from="255" to="65535"><description><lang xml:lang="en">Range of red color value.</lang></description></value><value from="65536" to="16777215"><description><lang xml:lang="en">Range of green color value.</lang></description></value><value from="16777215" to="2147483647"><description><lang xml:lang="en">Range of blue color value.</lang></description></value></configParam><configParam number="80" size="1" default="0" type="rangemapped"><name><lang xml:lang="en">Enable/Disable to send notifications to associated devices to associated devices.</lang></name><description><lang xml:lang="en">This parameter is used to Enable/Disable to send notifications to associated devices (in Group 1) when the state of Smart Switch Gen5s load is changed. (0=Send nothing, 1=Send hail CC, 2=Send basic report CC).</lang></description><value from="2" to="2"><description><lang xml:lang="en">Send BASIC Report Command</lang></description></value><value from="0" to="0"><description><lang xml:lang="en">Send Nothing (Disabled)</lang></description></value><value from="1" to="1"><description><lang xml:lang="en">Send HAIL Command</lang></description></value></configParam><configParam number="81" size="1" default="0" type="rangemapped"><name><lang xml:lang="en">Configure the state of LED</lang></name><description><lang xml:lang="en">This parameter is used to configure the LED state when the Smart Switch is in Energy mode/Momentary indicate mode/Night light mode.</lang></description><value from="1" to="1"><description><lang xml:lang="en">The state of LED will follow with the output load state, but will turn off after 5 seconds if there is no any switch action.(Momentary indicate mode)</lang></description></value><value from="2" to="2"><description><lang xml:lang="en">The state of LED will the same with Night light mode state configured by parameter 83. </lang></description></value><value from="0" to="0"><description><lang xml:lang="en">The state of LED will follow with the output load state(Energy mode)</lang></description></value></configParam><configParam number="83" size="4" default="14524637" type="rangemapped"><name><lang xml:lang="en">Configure the LED indication status when it is in Night light mode</lang></name><description><lang xml:lang="en">This parameter is used to configure the LED indication status when the current mode is Night light mode.</lang></description><value from="0" to="255"><description><lang xml:lang="en">Set the indication value of red Led. </lang></description></value><value from="256" to="65535"><description><lang xml:lang="en">Set the indication value of green Led.</lang></description></value><value from="65536" to="16777215"><description><lang xml:lang="en">Set the indication value of blue Led.</lang></description></value></configParam><configParam number="84" size="1" default="50" type="range"><name><lang xml:lang="en">Configure the brightness level for the LED indication</lang></name><description><lang xml:lang="en">This parameter is used to configure the brightness level for the LED indication.Brightness level range is 0 to 100%.</lang></description><value from="0" to="100"><description><lang xml:lang="en">Brightness level range is 0 to 100%.</lang></description></value></configParam><configParam number="90" size="1" default="1" type="rangemapped"><name><lang xml:lang="en">Enable/Disable the function of parameter 91 and 92.</lang></name><description><lang xml:lang="en">This parameter is used to Enable/Disable the function of parameter 91 and 92 (1=Enabled, 0=Disabled).</lang></description><value from="0" to="0"><description><lang xml:lang="en">Configuration Parameters 91 and 92 are Disabled</lang></description></value><value from="1" to="1"><description><lang xml:lang="en">Configuration Parameters 91 and 92 are Enabled</lang></description></value></configParam><configParam number="91" size="2" default="25" type="range"><name><lang xml:lang="en">Induce an automatic report</lang></name><description><lang xml:lang="en">This parameter is used to induce an automatic report when the change of the current power is more/less than the threshold in wattage.</lang></description><value from="0" to="32767"><description><lang xml:lang="en">The threshold can be set from 0 to 32767 watt.</lang></description></value></configParam><configParam number="92" size="1" default="5" type="range"><name><lang xml:lang="en">Induce an automatic report</lang></name><description><lang xml:lang="en">This parameter is used to induce an automatic report when the change of the current power is more/less than the threshold in percentage.</lang></description><value from="0" to="100"><description><lang xml:lang="en">The threshold can be set from 0 to 100 percent.</lang></description></value></configParam></configParams><resourceLinks><deviceImage url="https://products.z-wavealliance.org/ProductImages/Index?productName=ZC10-15110005"/></resourceLinks></ZWaveDevice>
