<?xml version="1.0" encoding="utf-8"?>
<ZWaveDevice xmlns="http://www.pepper1.net/zwavedb/xml-schemata/z-wave" schemaVersion="2"><descriptorVersion>1</descriptorVersion><deviceData><manufacturerId value="0118"/><productType value="0808"/><productId value="0808"/><libType value="03"/><protoVersion value="05"/><protoSubVersion value="03"/><appVersion value="02"/><appSubVersion value="00"/><basicClass value="04"/><genericClass value="00"/><specificClass value="00"/><beamSensor>0</beamSensor><certNumber>ZC08-15060003</certNumber><rfFrequency>EU</rfFrequency></deviceData><deviceDescription><description><lang xml:lang="en">Z-Wave dimmer switch</lang></description><productName>TKB TZ35D Dimmer</productName><brandName>TKB Home</brandName><productCode>TZ35D</productCode></deviceDescription><commandClasses><commandClass id="0086" supported="true" controlled="false"/></commandClasses><resourceLinks><deviceImage url="https://products.z-wavealliance.org/ProductImages/Index?productName=ZC08-15060003"/></resourceLinks></ZWaveDevice>
