<?xml version="1.0" encoding="utf-8"?>
<ZWaveDevice xmlns="http://www.pepper1.net/zwavedb/xml-schemata/z-wave" schemaVersion="2"><descriptorVersion>1</descriptorVersion><deviceData><manufacturerId value="0068"/><productType value="0003"/><productId value="0009"/><protoVersion value="06"/><protoSubVersion value="51"/><appVersion value="00"/><appSubVersion value="00"/><basicClass value="03"/><genericClass value="00"/><specificClass value="00"/><beamSensor>0</beamSensor><certNumber>ZC10-17015396</certNumber><rfFrequency>EU</rfFrequency></deviceData><deviceDescription><description><lang xml:lang="en">The Door/Window Sensor is a wireless, battery powered, Z-Wave compatible reed sensor.Each time the sensors body and a magnet separate, a radio signal is sent.In addition, the Door/Window Sensor supports one potential-free input and self-power adapter of DC 9V~30V.The Door/Window Sensor is designed for use with home automation systems, alarm and surveillance systems and everywhere else where information related to opening/closing of doors, garage, gates.</lang></description><productName>Door/Window Sensor</productName><brandName>Good Way Technology, Co., Ltd</brandName><productCode>TS2001</productCode></deviceDescription><commandClasses/><assocGroups><assocGroup number="1" maxNodes="1"><description><lang xml:lang="en">Group1:u0022Lifelineu0022 :Group1 is used to send Sensor trigger status(BATTERY, NOTIFICATION, DEVICE_RESET_LOCALLY NOTIFICATION) to the controller.</lang></description></assocGroup><assocGroup number="2" maxNodes="5"><description><lang xml:lang="en">Group2:u0022Sensor Reed repu0022:When the Sensor Reed rep is triggered, a NOTIFICATION REPORT is sent to the Device in Group2.</lang></description></assocGroup><assocGroup number="3" maxNodes="5"><description><lang xml:lang="en">Group3:u0022Sensor Tamper repu0022:When the Sensor Tamper rep is triggered, a NOTIFICATION REPORT is sent to the Device in Group3.</lang></description></assocGroup><assocGroup number="4" maxNodes="5"><description><lang xml:lang="en">Group4:u0022Sensor S1 repu0022: When the Sensor S1 rep is triggered, a NOTIFICATION REPORT is sent to the Device in Group4.</lang></description></assocGroup><assocGroup number="5" maxNodes="5"><description><lang xml:lang="en">Group5:u0022Sensor S2 repu0022:When the Sensor S2 rep is triggered, a NOTIFICATION REPORT is sent to the Device in Group5.</lang></description></assocGroup></assocGroups><configParams><configParam number="1" size="1" default="3" type="range"><name><lang xml:lang="en">Battery Report delay time</lang></name><description><lang xml:lang="en">The interval time of sending Battery Report when the battery runs out of electricity.</lang></description><value from="1" to="30"><description><lang xml:lang="en">minute</lang></description></value></configParam><configParam number="2" size="1" default="0" type="range"><name><lang xml:lang="en">External Sensor Define</lang></name><description><lang xml:lang="en">Set the configuration of 2 external sensors.0 (00b): S1 NO, S2 NO1 (01b):S1 NO,S2 NC2 (10b):S1 NC,S2 NO3 (11b):S1 NC,S2 NC</lang></description><value from="0" to="3"><description><lang xml:lang="en">External Sensor Define</lang></description></value></configParam></configParams><resourceLinks><deviceImage url="https://products.z-wavealliance.org/ProductImages/Index?productName=ZC10-17015396"/></resourceLinks></ZWaveDevice>
