<?xml version="1.0" encoding="utf-8"?>
<ZWaveDevice xmlns="http://www.pepper1.net/zwavedb/xml-schemata/z-wave" schemaVersion="2"><descriptorVersion>1</descriptorVersion><deviceData><manufacturerId value="018E"/><productType value="0002"/><productId value="0011"/><protoVersion value="06"/><protoSubVersion value="61"/><appVersion value="00"/><appSubVersion value="00"/><basicClass value="03"/><genericClass value="00"/><specificClass value="00"/><beamSensor>0</beamSensor><certNumber>ZC10-17055618</certNumber><rfFrequency>EU</rfFrequency></deviceData><deviceDescription><description><lang xml:lang="en">BX-35ZW bell box is a battery-operated wireless outdoor siren generating a loud 105 decibel siren sound and strobe lights during an alarm to provide visible and audible alerts. Encased in a durable, IPX5 waterproof elegant design, easy-to-install BX-35ZW is a premium choice for the modern smart home.The BX-35ZW is energy saving and environmentally conscious, requiring only two Alkaline batteries, yet still has a long battery life of up to 3.5 years. The BX-35ZW generates unique alarm sounds for fire and burglary to inform users of the type of danger at hand. It provides programmable siren duration of 3, 5, and 10 minutes.In addition to producing audible and visible warnings in the case of emergency, the BX-35ZW emits beep notifications for arming and disarming of a security system, and of its low battery status. Its tamper-deterrent feature protects against unauthorized removal and sabotage. The BX-35ZW is compatible with others Z-Wave systems.</lang></description><productName>Bellbox</productName><brandName>Climax Technology</brandName><productCode>BX-35ZW</productCode></deviceDescription><commandClasses/><assocGroups><assocGroup number="1" maxNodes="1"><description><lang xml:lang="en">Group 1 for LifeLine (maximum node:1):Battery CC (COMMAND_CLASS_BATTERY)Notification CC,V4 (COMMAND_CLASS_NOTIFICATION)SwitchBinary CC, V1 (COMMAND_CLASS_SWITCH_BINARY)Device Reset Locally CC</lang></description></assocGroup><assocGroup number="2" maxNodes="5"><description><lang xml:lang="en">Group 2 for Tamp rep (maximum node: 5):Notification CC,V4 (COMMAND_CLASS_NOTIFICATION)When Tamper Open, Group 2 send Notification(Type:07,Event:03), Tamper Close send Notification(Type:07,Event:00,Parameter:03)</lang></description></assocGroup><assocGroup number="3" maxNodes="5"><description><lang xml:lang="en">Group 3 for AC rep (maximum node: 5):Notification CC,V4 (COMMAND_CLASS_NOTIFICATION)When AC Fail send Notification (Type:08,Event:02),When AC Restore send Notification (Type:08, Event:03)</lang></description></assocGroup></assocGroups><configParams><configParam number="1" size="1" default="10" type="range"><name><lang xml:lang="en">Alarm Length</lang></name><description><lang xml:lang="en">Maximum siren length.0x01~0x0A (1~10 min), default 0x0A.</lang></description><value from="1" to="10"><description><lang xml:lang="en">1 minute to 10 minutes</lang></description></value></configParam><configParam number="2" size="1" default="1" type="range"><name><lang xml:lang="en">Alarm LED Flash</lang></name><description><lang xml:lang="en">Upon siren trigger, LED flash enable/disable.0x00: disable, 0x01: enable; default 0x01</lang></description><value from="0" to="1"><description><lang xml:lang="en">0:disable, 1: enable</lang></description></value></configParam><configParam number="3" size="1" default="0" type="range"><name><lang xml:lang="en">Comfort LED</lang></name><description><lang xml:lang="en">Comfort LED flash every sec, 0~250sec, each unit is 10 sec.0x00~0x19 (disable, 10sec,,250sec)default:0x00</lang></description><value from="0" to="25"><description><lang xml:lang="en">0 sec to 250 sec, the unit is 10 sec</lang></description></value></configParam><configParam number="4" size="1" default="1" type="range"><name><lang xml:lang="en">Tamper</lang></name><description><lang xml:lang="en">Tamper Enable/Disable0x00:disable, 0x01: enabledefault 0x01</lang></description><value from="0" to="1"><description><lang xml:lang="en">0:disable, 1: enable</lang></description></value></configParam></configParams><resourceLinks><deviceImage url="https://products.z-wavealliance.org/ProductImages/Index?productName=ZC10-17055618"/></resourceLinks></ZWaveDevice>
