<?xml version="1.0" encoding="utf-8"?>
<ZWaveDevice xmlns="http://www.pepper1.net/zwavedb/xml-schemata/z-wave" schemaVersion="2"><descriptorVersion>1</descriptorVersion><deviceData><manufacturerId value="0371"/><productType value="0102"/><productId value="0005"/><protoVersion value="06"/><protoSubVersion value="71"/><appVersion value="00"/><appSubVersion value="00"/><basicClass value="03"/><genericClass value="00"/><specificClass value="00"/><beamSensor>0</beamSensor><certNumber>ZC10-18056128</certNumber><rfFrequency>US</rfFrequency></deviceData><deviceDescription><description><lang xml:lang="en">Aeotec TriSensor is a universal Z-Wave Plus compatible product, consists of temperature, lighting and motion sensors, powered by a CR123A battery. It can be included and operated in any Z-Wave network with other Z-Wave certified devices from other manufacturers and/or other applications. By the built-in motion sensor, an alam will be sent to the gateway when the motion sensor is triggered.</lang></description><productName>TriSensor</productName><brandName>Aeotec</brandName><productCode>ZWA005-A</productCode></deviceDescription><commandClasses/><assocGroups><assocGroup number="1" maxNodes="5"><description><lang xml:lang="en">Group 1 is lifeline group; all nodes which associated in this group will receive the messages sent by device throughlifeline.CommandClass:COMMAND_CLASS_NOTIFICATIONCOMMAND_CLASS_SENSOR_BINARY COMMAND_CLASS_SENSOR_MULTILEVEL COMMAND_CLASS_BATTERY COMMAND_CLASS_DEVICE_RESET_LOCALLYCommand:NOTIFICATION_REPORT SENSOR_BINARY_REPORTSENSOR_MULTILEVEL_REPORT BATTERY_REPORT DEVICE_RESET_LOCALLY_NOTIFICATION</lang></description></assocGroup><assocGroup number="2" maxNodes="5"><description><lang xml:lang="en">Group 2 is controlling group, all nodes associated in this group will be controlled through BASIC_SET command by the device when device detects a movement event. Basic Set Value is decided by Configuration Parameter 6.CommandClass:COMMAND_CLASS_BASIC (HomeSecurity)Command:BASIC_SET</lang></description></assocGroup><assocGroup number="3" maxNodes="5"><description><lang xml:lang="en">Group 3 is controlling group, all nodes associated in this group will be controlled through BASIC_SET command by the device when device detects an ambient temperature alarm (Decided by Configuration Parameter 7).CommandClass:COMMAND_CLASS_BASIC(Temperature)Command:BASIC_SET</lang></description></assocGroup></assocGroups><configParams><configParam number="1" size="2" default="30" type="range"><name><lang xml:lang="en">Motion Retrigger Time</lang></name><description><lang xml:lang="en">This parameter is configured the delay time before PIR sensor can be triggered again to reset motion timeout counter. Value = 0 will disable PIR sensor from triggering until motion timeout has finished.</lang></description><value from="0" to="32767"><description><lang xml:lang="en"> Value = 0 will disable PIR sensor from triggering until motion timeout has finished.</lang></description></value></configParam><configParam number="10" size="1" default="1" type="range"><name><lang xml:lang="en">Led Indicate Disable</lang></name><description><lang xml:lang="en">This parameter is configured the Led light on disable or enable. 1Enable Led Blink when device detects a motion event.0Disable Led Blink. This configuration is not affect inclusion, exclusion and reset.</lang></description><value from="0" to="1"><description><lang xml:lang="en"> 1Enable Led Blink when device detects a motion event. 0Disable Led Blink. This configuration is not affect inclusion, exclusion and reset.</lang></description></value></configParam><configParam number="100" size="2" default="1024" type="range"><name><lang xml:lang="en">Light Sensor Calibrated Coefficient</lang></name><description><lang xml:lang="en">This configuration defines the calibrated scale for ambient light intensity. Because the method and position that the sensor mounted and the cover of sensor will bring measurement error, user can get more real light intensity by this parameter setting. User should run the steps as blows for calibrating1)Set this parameter value to default (Assumes the sensor has been added in a Z- Wave Network).2)Place a digital luxmeter close to sensor and keep the same direction, monitor the light intensity value (Vm) which report to controller and record it. The same time user should record the value (Vs) of luxmeter.3)The scale calibration formula: k = Vm / Vs.4)The value of k is then multiplied by 1024 and rounded to the nearest whole number.5)Set the value getting in 5) to this parameter, calibrate finished. For example, Vm = 300, Vs =2600, then k = 2600 /300 = 8.6667 k = 8.6667 * 1024 = 8874.78875The parameter should be set to 8875.</lang></description><value from="1" to="32767"><description><lang xml:lang="en">Scale: Lux.</lang></description></value></configParam><configParam number="11" size="1" default="2" type="range"><name><lang xml:lang="en">Led Color For Motion Event Report </lang></name><description><lang xml:lang="en">0Disable.1Red.2Green.3Blue.4Yellow.5Pink.6Cyan.7Purple.8Orange.</lang></description><value from="0" to="8"><description><lang xml:lang="en">0Disable. 1Red. 2Green. 3Blue. 4Yellow. 5Pink. 6Cyan. 7Purple. 8Orange.</lang></description></value></configParam><configParam number="12" size="1" default="0" type="range"><name><lang xml:lang="en">Led Color For Temperature Sensor Report </lang></name><description><lang xml:lang="en">0Disable.1Red.2 Green.3Blue.4Yellow.5Pink.6Cyan.7Purple.8Orange.</lang></description><value from="0" to="8"><description><lang xml:lang="en">0Disable. 1Red. 2 Green. 3Blue. 4Yellow. 5Pink. 6Cyan. 7Purple. 8Orange.</lang></description></value></configParam><configParam number="13" size="1" default="0" type="range"><name><lang xml:lang="en">Led Color For Light Sensor Report </lang></name><description><lang xml:lang="en">0Disable.1Red.2 Green.3Blue.4Yellow.5Pink.6Cyan.7Purple.8Orange</lang></description><value from="0" to="8"><description><lang xml:lang="en">0Disable. 1Red. 2 Green. 3Blue. 4Yellow. 5Pink. 6Cyan. 7Purple. 8Orange</lang></description></value></configParam><configParam number="14" size="1" default="0" type="range"><name><lang xml:lang="en">Led Color For Battery Report </lang></name><description><lang xml:lang="en">0Disable.1Red.2 Green.3Blue.4Yellow.5Pink.6Cyan.7Purple.8Orange.</lang></description><value from="0" to="8"><description><lang xml:lang="en">0Disable. 1Red. 2 Green. 3Blue. 4Yellow. 5Pink. 6Cyan. 7Purple. 8Orange.</lang></description></value></configParam><configParam number="15" size="1" default="0" type="range"><name><lang xml:lang="en">Led Color For Wakeup Notification Report </lang></name><description><lang xml:lang="en">0Disable.1Red.2 Green.3Blue.4Yellow.5Pink.6Cyan.7Purple.8Orange.</lang></description><value from="0" to="8"><description><lang xml:lang="en">0Disable. 1Red. 2 Green. 3Blue. 4Yellow. 5Pink. 6Cyan. 7Purple. 8Orange.</lang></description></value></configParam><configParam number="2" size="2" default="240" type="range"><name><lang xml:lang="en">Motion Clear Time</lang></name><description><lang xml:lang="en">This parameter is configured the time to clear motion event after a motion event detected. Time to motion clear, the device will send a clear event report to controller and send BASIC_SET= 0x00 to nodes associated in group 2. Unit: Second.</lang></description><value from="1" to="32767"><description><lang xml:lang="en">Unit: Second.</lang></description></value></configParam><configParam number="20" size="1" default="1" type="range"><name><lang xml:lang="en">Temperature Scale Setting</lang></name><description><lang xml:lang="en">Configure temperature sensor scale type, Temperature to report in Celsius or Fahrenheit. 0Celsius (C).1Fahrenheit (F).</lang></description><value from="0" to="1"><description><lang xml:lang="en"> 0Celsius (C). 1Fahrenheit (F).</lang></description></value></configParam><configParam number="21" size="2" default="20" type="range"><name><lang xml:lang="en">Temperature Threshold Value to Report</lang></name><description><lang xml:lang="en">Change threshold value for change in temperature to induce an automatic report for temperature sensor. Scale is identical setting in Parameter No.20.Setting of value 20 can be a change of -2.0 or +2.0 (C or F depending on Parameter No.20) to induce automatic report or setting a value of 2 will be a change of 0.2(C or F).</lang></description><value from="0" to="250"><description><lang xml:lang="en">Temperature Threshold Value</lang></description></value></configParam><configParam number="22" size="2" default="100" type="range"><name><lang xml:lang="en">Light intensity Threshold Value to Report</lang></name><description><lang xml:lang="en">Change threshold value for change in light sensor to induce an automatic report for temperature sensor. Scale: Lux.</lang></description><value from="0" to="10000"><description><lang xml:lang="en">Scale: Lux.</lang></description></value></configParam><configParam number="23" size="2" default="3600" type="range"><name><lang xml:lang="en">Temperature Sensor Report Interval</lang></name><description><lang xml:lang="en">This parameter is configured the time interval for temperature sensor report. This value is larger, the battery life is longer. And the temperature value changed is not obvious.Unit: Second.</lang></description><value from="1" to="32767"><description><lang xml:lang="en">Unit: Second.</lang></description></value></configParam><configParam number="24" size="2" default="3600" type="range"><name><lang xml:lang="en">Light Sensor Report Interval</lang></name><description><lang xml:lang="en">This parameter is configured the time interval for light sensor report. This value is larger, the battery life is longer. And the light intensity changed is not obvious.Unit: Second.</lang></description><value from="1" to="32767"><description><lang xml:lang="en">Unit: Second.</lang></description></value></configParam><configParam number="3" size="1" default="11" type="range"><name><lang xml:lang="en">Motion Sensitivity</lang></name><description><lang xml:lang="en">This parameter is configured the sensitivity that motion detect.0PIR sensor disabled.1Lowest sensitivity. 11 Highest sensitivity</lang></description><value from="0" to="11"><description><lang xml:lang="en">0PIR sensor disabled. 1Lowest sensitivity.11 Highest sensitivity</lang></description></value></configParam><configParam number="30" size="2" default="0" type="range"><name><lang xml:lang="en">Temperature Offset Value</lang></name><description><lang xml:lang="en">The current measuring temperature value can be add and minus a value by this setting. The scale can be decided by Parameter Number 20.Temperature Offset Value = [Value] * 0.1(Celsius / Fahrenheit)</lang></description><value from="-200" to="200"><description><lang xml:lang="en">Temperature Offset Value = [Value] * 0.1(Celsius / Fahrenheit)</lang></description></value></configParam><configParam number="31" size="2" default="0" type="range"><name><lang xml:lang="en">Light Intensity Offset Value</lang></name><description><lang xml:lang="en">The current measuring light intensity value can be add and minus a value by this setting.</lang></description><value from="-1000" to="1000"><description><lang xml:lang="en">Scale: Lux.</lang></description></value></configParam><configParam number="4" size="1" default="0" type="range"><name><lang xml:lang="en">Binary Sensor Report Enable</lang></name><description><lang xml:lang="en">0 Disable sensor binary report when motion event is detected or cleared. 1 Enable sensor binary report when motion event is detected or cleared.</lang></description><value from="0" to="1"><description><lang xml:lang="en">0 Disable sensor binary report when motion event is detected or cleared. 1 Enable sensor binary report when motion event is detected or cleared.</lang></description></value></configParam><configParam number="5" size="1" default="3" type="range"><name><lang xml:lang="en">Disable BASIC_SET to Associated nodes</lang></name><description><lang xml:lang="en">This parameter is configured the enabled or disabled send BASIC_SET command to nodes that associated in group 2 and group 3.0Disabled All Group Basic Set Command1Enabled Group 2 Basic Set Command, Group 3 Basic Set Command is disabled. 2Enabled Group 3 Basic SetCommand, Group 2 Basic Set Command is disabled. 3Enabled Group 2 and Group 3 Basic Set Command.</lang></description><value from="0" to="3"><description><lang xml:lang="en">0Disabled All Group Basic Set Command 1Enabled Group 2 Basic Set Command, Group 3 Basic Set Command is disabled.2Enabled Group 3 Basic SetCommand, Group 2 Basic Set Command is disabled. 3Enabled Group 2 and Group 3 Basic Set Command.</lang></description></value></configParam><configParam number="6" size="1" default="0" type="range"><name><lang xml:lang="en">Basic Set Value Settings for Group 2</lang></name><description><lang xml:lang="en">0Send BASIC_SET = 0xFF to devices associated in Group 2 when motion event is triggered, send BASIC_SET = 0x00 to devices associated in group 2 when motion event is cleared.1 Send BASIC_SET = 0x00 to devices associated in Group 2 when motion event is triggered, send BASIC_SET = 0xFF to devices associated in group 2 when motion event is cleared.2Send BASIC_SET = 0xFF to devices associated in Group 2 when motion event is triggered.3Send BASIC_SET = 0x00 to devices associated in Group 2 when motion event is triggered.4Send BASIC_SET = 0x00 to devices associated in Group 2 when motion event is cleared. 5Send BASIC_SET = 0xFF to devices associated in Group 2 when motion event is cleared.</lang></description><value from="0" to="5"><description><lang xml:lang="en">1 Send BASIC_SET = 0x00 to devices associated in Group 2 when motion event is triggered, send BASIC_SET = 0xFF to devices associated in group 2 when motion event is cleared. 2Send BASIC_SET = 0xFF to devices associated in Group 2 when motion event is triggered. 3Send BASIC_SET = 0x00 to devices associated in Group 2 when motion event is triggered. 4Send BASIC_SET = 0x00 to devices associated in Group 2 when motion event is cleared. 5Send BASIC_SET = 0xFF to devices associated in Group 2 when motion event is cleared.</lang></description></value></configParam><configParam number="7" size="2" default="750" type="range"><name><lang xml:lang="en">Temperature Alarm Value</lang></name><description><lang xml:lang="en">This parameter is configured the threshold value that alarm level for temperature. When the current ambient temperature value is larger than this configuration value, device will send a BASIC_SET = 0xFF to nodes associated in group 3. If current temperature value is less than this value, device will send a BASIC_SET = 0x00 to nodes associated in group 3.Value = [Value]0.1(Celsius / Fahrenheit)</lang></description><value from="-400" to="1185"><description><lang xml:lang="en">Value = [Value]0.1(Celsius / Fahrenheit)</lang></description></value></configParam></configParams><resourceLinks><deviceImage url="https://products.z-wavealliance.org/ProductImages/Index?productName=ZC10-18056128"/></resourceLinks></ZWaveDevice>
